mortardata/__init__.py
mortardata-0.1.8.dist-info/METADATA
mortardata-0.1.8.dist-info/WHEEL
mortardata-0.1.8.dist-info/RECORD
