Metadata-Version: 2.1
Name: mortardata
Version: 0.1.8
Summary: 
License: BSD-3-Clause
Author: Gabe Fierro
Author-email: gtfierro@mines.edu
Requires-Python: >=3.10,<4.0
Classifier: License :: OSI Approved :: BSD License
Classifier: Programming Language :: Python :: 3
Classifier: Programming Language :: Python :: 3.10
Classifier: Programming Language :: Python :: 3.11
Classifier: Programming Language :: Python :: 3.12
Requires-Dist: grequests (>=0.7.0,<0.8.0)
Requires-Dist: loguru (>=0.7.0,<0.8.0)
Requires-Dist: pandas (>=2.0.3,<3.0.0)
Requires-Dist: pyarrow (>=12.0.1,<13.0.0)
Requires-Dist: rdflib (>=6.3.2,<7.0.0)
Requires-Dist: requests (>=2.31.0,<3.0.0)
Requires-Dist: tqdm (>=4.65.0,<5.0.0)
